script_grabber/__init__.py
script_grabber/grabber.py
script_grabber/grabexceptions.py
script_grabber/grabmaster.py
script_grabber-0.1.4.dist-info/LICENSE
script_grabber-0.1.4.dist-info/METADATA
script_grabber-0.1.4.dist-info/WHEEL
script_grabber-0.1.4.dist-info/entry_points.txt
script_grabber-0.1.4.dist-info/RECORD
