Metadata-Version: 2.1
Name: script-grabber
Version: 0.1.4
Summary: A job queue management system for distributed computing.
License: MIT
Author: Meir Michanie
Author-email: meirm@riunx.com
Requires-Python: >=3.9,<4.0
Classifier: License :: OSI Approved :: MIT License
Classifier: Programming Language :: Python :: 3
Classifier: Programming Language :: Python :: 3.9
Classifier: Programming Language :: Python :: 3.10
Classifier: Programming Language :: Python :: 3.11
Classifier: Programming Language :: Python :: 3.12
